navigaattori/__init__.py
navigaattori/__main__.py
navigaattori/api.py
navigaattori/approvals.py
navigaattori/bind.py
navigaattori/changes.py
navigaattori/cli.py
navigaattori/eject.py
navigaattori/fs.py
navigaattori/layout.py
navigaattori/liitos_meta.py
navigaattori/meta.py
navigaattori/structures.py
navigaattori/template_loader.py
navigaattori/vcs.py
navigaattori/templates/liitos_vocabulary.yml
navigaattori-2023.12.4.dist-info/LICENSE
navigaattori-2023.12.4.dist-info/METADATA
navigaattori-2023.12.4.dist-info/WHEEL
navigaattori-2023.12.4.dist-info/entry_points.txt
navigaattori-2023.12.4.dist-info/top_level.txt
navigaattori-2023.12.4.dist-info/RECORD
